aisexplorer/AIS.py
aisexplorer/Exceptions.py
aisexplorer/Filters.py
aisexplorer/Proxy.py
aisexplorer/Utils/Utility.py
aisexplorer/__init__.py
aisexplorer-0.2.2.dist-info/METADATA
aisexplorer-0.2.2.dist-info/WHEEL
aisexplorer-0.2.2.dist-info/RECORD
