Metadata-Version: 2.1
Name: AISExplorer
Version: 0.2.2
Summary: Wrapper to fetch data from marinetraffic
Home-page: https://github.com/reyemb/AISExplorer
Keywords: AIS,Vessel,Shiptracking,Shiplocation,Location,Proxy,marinetraffic
Author: reyemb
Author-email: info@reyemb.io
Requires-Python: >=3.9
Classifier: Programming Language :: Python :: 3
Classifier: Programming Language :: Python :: 3.9
Classifier: Programming Language :: Python :: 3.10
Classifier: Programming Language :: Python :: 3.11
Classifier: Programming Language :: Python :: 3.12
Requires-Dist: lxml (>=4.6.4)
Requires-Dist: numpy (>=1.26.2,<2.0.0)
Requires-Dist: pandas (>=1.3.4)
Requires-Dist: requests (>=2.26.0)
Requires-Dist: tenacity (>=8.0.1)
Project-URL: Repository, https://github.com/reyemb/AISExplorer
